idahelper/__init__.py
idahelper/_utils.py
idahelper/comments.py
idahelper/cpp.py
idahelper/file_format.py
idahelper/functions.py
idahelper/instructions.py
idahelper/memory.py
idahelper/objc.py
idahelper/segments.py
idahelper/strings.py
idahelper/tif.py
idahelper/widgets.py
idahelper/xrefs.py
idahelper/ast/__init__.py
idahelper/ast/cexpr.py
idahelper/ast/cfunc.py
idahelper/ast/cinsn.py
idahelper/ast/lvars.py
idahelper/microcode/__init__.py
idahelper/microcode/mba.py
idahelper/microcode/mblock.py
idahelper/microcode/mcallarg.py
idahelper/microcode/minsn.py
idahelper/microcode/mop.py
idahelper/microcode/mreg.py
idahelper/microcode/optimizers.py
idahelper/microcode/visitors.py
idahelper/pac/__init__.py
idahelper/pac/pac_interface.py
idahelper/pac/pacxplorer/__init__.py
idahelper/pac/pacxplorer/pac_client.py
idahelper/pac/pacxplorerng/__init__.py
idahelper/pac/pacxplorerng/definitions.py
idahelper/pac/pacxplorerng/pac_client.py
idahelper-1.0.17.dist-info/METADATA
idahelper-1.0.17.dist-info/WHEEL
idahelper-1.0.17.dist-info/licenses/LICENSE
idahelper-1.0.17.dist-info/RECORD
